cornflower/__init__.py
cornflower/message.py
cornflower/message_queue.py
cornflower/options.py
cornflower/utils.py
cornflower-0.1.0.dist-info/WHEEL
cornflower-0.1.0.dist-info/METADATA
cornflower-0.1.0.dist-info/RECORD
