Metadata-Version: 2.1
Name: cornflower
Version: 0.1.0
Summary: Library for writting simple AMQP handlers with type hints and pydantic support
Home-page: https://github.com/jakub-figat/cornflower
License: MIT
Author: jakub-figat
Requires-Python: >=3.9,<4.0
Classifier: License :: OSI Approved :: MIT License
Classifier: Programming Language :: Python :: 3
Classifier: Programming Language :: Python :: 3.10
Classifier: Programming Language :: Python :: 3.9
Requires-Dist: kombu (>=5.2.3,<6.0.0)
Requires-Dist: pika (>=1.2.0,<2.0.0)
Requires-Dist: pydantic (>=1.9.0,<2.0.0)
Project-URL: Repository, https://github.com/jakub-figat/cornflower
